sabrmetrics/__init__.py
sabrmetrics/playerids.py
sabrmetrics/mlb/__init__.py
sabrmetrics/mlb/address.py
sabrmetrics/mlb/divisions.py
sabrmetrics/mlb/leagues.py
sabrmetrics/mlb/scraper.py
sabrmetrics/mlb/standings.py
sabrmetrics/sfbb/__init__.py
sabrmetrics/sfbb/_tools.py
sabrmetrics-0.6.0.dist-info/LICENSE
sabrmetrics-0.6.0.dist-info/METADATA
sabrmetrics-0.6.0.dist-info/WHEEL
sabrmetrics-0.6.0.dist-info/top_level.txt
sabrmetrics-0.6.0.dist-info/RECORD
